finemotion/__init__.py
finemotion/emotion.py
finemotion/data/all_en_merged.json
finemotion/data/investopedia.json
finemotion/data/nrc_en.json
finemotion/data/nrc_en_merged.json
finemotion/data/text2emotion.tsv
tests/__init__.py
tests/test_emotion.py
finemotion-1.0.0.dist-info/LICENSE
finemotion-1.0.0.dist-info/METADATA
finemotion-1.0.0.dist-info/WHEEL
finemotion-1.0.0.dist-info/top_level.txt
finemotion-1.0.0.dist-info/RECORD
