Metadata-Version: 2.1
Name: finemotion
Version: 1.0.0
Summary: Our emotional annotation algorithm is built upon the foundation laid by the Text2Emotion project, with a series of key enhancements aimed at optimizing its functionality for financial news analysis
Home-page: https://github.com/AI4Finance-Foundation/Fin-Emotion
Author: AliceNN-ucdenver
Author-email: shawn.mccarthy@ucdenver.edu
License: MIT
License-File: LICENSE
Requires-Dist: spacy
Requires-Dist: nltk
Requires-Dist: contractions
